timermiddleware/__init__.py
TimerMiddleware-0.6.3.dist-info/LICENSE
TimerMiddleware-0.6.3.dist-info/METADATA
TimerMiddleware-0.6.3.dist-info/WHEEL
TimerMiddleware-0.6.3.dist-info/top_level.txt
TimerMiddleware-0.6.3.dist-info/RECORD
